lda/__init__.py
lda/config.py
lda/cli/__init__.py
lda/cli/commands.py
lda/cli/commands_docs.py
lda/cli/deprecation.py
lda/cli/docs_command.py
lda/cli/interactive.py
lda/cli/main.py
lda/cli/utils.py
lda/core/__init__.py
lda/core/errors.py
lda/core/manifest.py
lda/core/name_builder.py
lda/core/name_parser.py
lda/core/profile.py
lda/core/scaffold.py
lda/core/template_service.py
lda/core/tracking.py
lda/core/validation.py
lda/display/__init__.py
lda/display/console.py
lda/display/progress.py
lda/display/themes.py
lda/logging/__init__.py
lda/logging/formatters.py
lda/logging/lazy_logger.py
lda/logging/logger.py
lda/templates/readme/playground_readme.md.j2
lda/templates/readme/project_readme.md.j2
lda/templates/readme/section_readme.md.j2
lda/templates/scripts/python_playground.py.j2
lda/templates/scripts/python_run.py.j2
lda/templates/scripts/r_playground.R.j2
lda/templates/scripts/r_run.R.j2
ldanalysis-0.2.0.6.dist-info/licenses/LICENSE
ldanalysis-0.2.0.6.dist-info/METADATA
ldanalysis-0.2.0.6.dist-info/WHEEL
ldanalysis-0.2.0.6.dist-info/entry_points.txt
ldanalysis-0.2.0.6.dist-info/top_level.txt
ldanalysis-0.2.0.6.dist-info/RECORD
