Metadata-Version: 2.4
Name: ldanalysis
Version: 0.2.0.6
Summary: Linked Document Analysis - A provenance-driven project management system
Author-email: ErnieP <ernie@cincineuro.com>
License: MIT
Project-URL: Homepage, https://cincineuro.github.io/ldanalysis/
Project-URL: Documentation, https://cincineuro.github.io/ldanalysis/
Project-URL: Repository, https://github.com/cincineuro/ldanalysis
Project-URL: Issues, https://github.com/cincineuro/ldanalysis/issues
Project-URL: Changelog, https://github.com/cincineuro/ldanalysis/blob/main/CHANGELOG.md
Keywords: document-analysis,provenance,project-management,tracking,scientific-computing
Classifier: Development Status :: 3 - Alpha
Classifier: Intended Audience :: Science/Research
Classifier: Topic :: Scientific/Engineering :: Information Analysis
Classifier: License :: OSI Approved :: MIT License
Classifier: Programming Language :: Python :: 3
Classifier: Programming Language :: Python :: 3.8
Classifier: Programming Language :: Python :: 3.9
Classifier: Programming Language :: Python :: 3.10
Classifier: Programming Language :: Python :: 3.11
Classifier: Programming Language :: Python :: 3.12
Requires-Python: >=3.8
License-File: LICENSE
Requires-Dist: pyyaml>=6.0
Requires-Dist: rich>=13.0
Requires-Dist: click>=8.1
Requires-Dist: jinja2>=3.0
Requires-Dist: build>=1.2.2.post1
Requires-Dist: twine>=6.1.0
Provides-Extra: dev
Requires-Dist: pytest>=7.0; extra == "dev"
Requires-Dist: pytest-cov>=4.0; extra == "dev"
Requires-Dist: black>=22.0; extra == "dev"
Requires-Dist: flake8>=5.0; extra == "dev"
Requires-Dist: mypy>=0.990; extra == "dev"
Requires-Dist: build>=1.2.0; extra == "dev"
Requires-Dist: twine>=6.0.0; extra == "dev"
Provides-Extra: docs
Requires-Dist: mkdocs>=1.5.0; extra == "docs"
Requires-Dist: mkdocs-material>=9.4.0; extra == "docs"
Requires-Dist: mkdocs-material-extensions>=1.3; extra == "docs"
Requires-Dist: mkdocs-minify-plugin>=0.7.0; extra == "docs"
Requires-Dist: pymdown-extensions>=10.0; extra == "docs"
Requires-Dist: mkdocs-git-revision-date-localized-plugin>=1.2.0; extra == "docs"
Requires-Dist: mike>=2.1.0; extra == "docs"
Provides-Extra: all
Requires-Dist: ldanalysis[dev,docs]; extra == "all"
Dynamic: license-file
